{
  "schema": 5,
  "resumo_status": [
    {
      "status": "Em pauta",
      "processos": 3,
      "registros": 3
    }
  ],
  "ancora_pauta": 23281,
  "watchlist": [],
  "resumo_temas": [
    {
      "tema": "Orçamento e execução",
      "total": 1,
      "nominais": 0,
      "data_ultimo_registro": "2026-05-19T00:00:00+00:00"
    },
    {
      "tema": "Regras fiscais",
      "total": 1,
      "nominais": 0,
      "data_ultimo_registro": "2026-05-19T00:00:00+00:00"
    }
  ],
  "resumo": [
    {
      "orgao": "MPO",
      "nome_completo": "Ministério do Planejamento e Orçamento",
      "total": 2,
      "por_fonte": {
        "Pauta": 2
      },
      "por_tema": {
        "Não classificado": 1,
        "Orçamento e execução": 1
      },
      "data_ultimo_registro": "2026-05-19T00:00:00+00:00"
    },
    {
      "orgao": "SOF",
      "nome_completo": "Secretaria de Orçamento Federal",
      "total": 1,
      "por_fonte": {
        "Pauta": 1
      },
      "por_tema": {
        "Regras fiscais": 1
      },
      "data_ultimo_registro": "2026-05-19T00:00:00+00:00"
    },
    {
      "orgao": "SEPLAN",
      "nome_completo": "Secretaria Nacional de Planejamento",
      "total": 0,
      "por_fonte": {},
      "por_tema": {},
      "data_ultimo_registro": null
    },
    {
      "orgao": "SMA",
      "nome_completo": "Secretaria de Monitoramento e Avaliação",
      "total": 0,
      "por_fonte": {},
      "por_tema": {},
      "data_ultimo_registro": null
    }
  ],
  "ultimos_andamentos": [
    {
      "fonte": "Pauta",
      "secao": "pauta",
      "status": "Em pauta",
      "status_descricao": "Aguardando julgamento em sessão marcada",
      "acordao": null,
      "orgaos": [
        "MPO"
      ],
      "temas": [],
      "confianca": "unidade_jurisdicionada",
      "vinculo": "principal",
      "classe": "materia",
      "relevancia": 3.0,
      "processo": "022.756/2025-6",
      "processo_id": "02275620256",
      "assunto": "Auditoria na gestão dos recursos públicos federais aplicados nas funções de governo  saúde, educação, assistência social, previdência, transportes, urbanismo e habitação,  no exercício de 2025",
      "unidade_jurisdicionada": "Ministério do Planejamento e Orçamento",
      "relator": "Benjamin Zymler",
      "colegiado": "Plenário",
      "natureza": null,
      "data": "2026-05-19T00:00:00+00:00",
      "data_sessao": "2026-05-19T00:00:00+00:00",
      "data_julgamento": null,
      "edicao_btcu": 23281,
      "link_tcu": null
    },
    {
      "fonte": "Pauta",
      "secao": "pauta",
      "status": "Em pauta",
      "status_descricao": "Aguardando julgamento em sessão marcada",
      "acordao": null,
      "orgaos": [
        "SOF"
      ],
      "temas": [
        "Regras fiscais"
      ],
      "confianca": "unidade_jurisdicionada",
      "vinculo": "compartilhado",
      "classe": "materia",
      "relevancia": 1.8,
      "processo": "024.241/2025-3",
      "processo_id": "02424120253",
      "assunto": "Acompanhamento dos relatórios de gestão fiscal referentes ao 2º quadrimestre de  2025, emitidos em cumprimento à Lei de Responsabilidade Fiscal",
      "unidade_jurisdicionada": "Câmara dos Deputados; Conselho Nacional de Justiça; Conselho Nacional do Ministério Público; Defensoria Pública da União; Justiça do Distrito Federal e Territórios (vinculador); Justiça do Trabalho (vinculador); Justiça Eleitoral (vinculador); Justiça Federal (vinculador); Justiça Militar (vinculador); Ministério Público da União; Presidência da República; Secretaria de Orçamento Federal; Secretaria do Tesouro Nacional; Senado Federal; Superior Tribunal de Justiça; Supremo Tribunal Federal; Tribunal de Contas da União",
      "relator": "Benjamin Zymler",
      "colegiado": "Plenário",
      "natureza": null,
      "data": "2026-05-19T00:00:00+00:00",
      "data_sessao": "2026-05-19T00:00:00+00:00",
      "data_julgamento": null,
      "edicao_btcu": 23281,
      "link_tcu": null
    },
    {
      "fonte": "Pauta",
      "secao": "pauta",
      "status": "Em pauta",
      "status_descricao": "Aguardando julgamento em sessão marcada",
      "acordao": null,
      "orgaos": [
        "MPO"
      ],
      "temas": [
        "Orçamento e execução"
      ],
      "confianca": "unidade_jurisdicionada",
      "vinculo": "compartilhado",
      "classe": "materia",
      "relevancia": 1.8,
      "processo": "025.632/2024-8",
      "processo_id": "02563220248",
      "assunto": "Auditoria operacional com aspectos de conformidade sobre a execução de  programas/projetos públicos custeados com recursos públicos que não transitam  diretamente pelo do Orçamento Geral da União",
      "unidade_jurisdicionada": "Banco Central do Brasil; Banco do Brasil S.a.; Banco Nacional de Desenvolvimento Econômico e Social; Caixa Econômica Federal; Empresa Gestora de Ativos; Ministério da Fazenda; Ministério do Planejamento e Orçamento",
      "relator": "Bruno Dantas",
      "colegiado": "Plenário",
      "natureza": null,
      "data": "2026-05-19T00:00:00+00:00",
      "data_sessao": "2026-05-19T00:00:00+00:00",
      "data_julgamento": null,
      "edicao_btcu": 23281,
      "link_tcu": null
    }
  ],
  "processos_detalhes": [
    {
      "fonte": "Pauta",
      "secao": "pauta",
      "status": "Em pauta",
      "status_descricao": "Aguardando julgamento em sessão marcada",
      "acordao": null,
      "orgaos": [
        "MPO"
      ],
      "temas": [],
      "confianca": "unidade_jurisdicionada",
      "vinculo": "principal",
      "classe": "materia",
      "relevancia": 3.0,
      "processo": "022.756/2025-6",
      "processo_id": "02275620256",
      "assunto": "Auditoria na gestão dos recursos públicos federais aplicados nas funções de governo  saúde, educação, assistência social, previdência, transportes, urbanismo e habitação,  no exercício de 2025",
      "unidade_jurisdicionada": "Ministério do Planejamento e Orçamento",
      "relator": "Benjamin Zymler",
      "colegiado": "Plenário",
      "natureza": null,
      "data": "2026-05-19T00:00:00+00:00",
      "data_sessao": "2026-05-19T00:00:00+00:00",
      "data_julgamento": null,
      "edicao_btcu": 23281,
      "link_tcu": null
    },
    {
      "fonte": "Pauta",
      "secao": "pauta",
      "status": "Em pauta",
      "status_descricao": "Aguardando julgamento em sessão marcada",
      "acordao": null,
      "orgaos": [
        "SOF"
      ],
      "temas": [
        "Regras fiscais"
      ],
      "confianca": "unidade_jurisdicionada",
      "vinculo": "compartilhado",
      "classe": "materia",
      "relevancia": 1.8,
      "processo": "024.241/2025-3",
      "processo_id": "02424120253",
      "assunto": "Acompanhamento dos relatórios de gestão fiscal referentes ao 2º quadrimestre de  2025, emitidos em cumprimento à Lei de Responsabilidade Fiscal",
      "unidade_jurisdicionada": "Câmara dos Deputados; Conselho Nacional de Justiça; Conselho Nacional do Ministério Público; Defensoria Pública da União; Justiça do Distrito Federal e Territórios (vinculador); Justiça do Trabalho (vinculador); Justiça Eleitoral (vinculador); Justiça Federal (vinculador); Justiça Militar (vinculador); Ministério Público da União; Presidência da República; Secretaria de Orçamento Federal; Secretaria do Tesouro Nacional; Senado Federal; Superior Tribunal de Justiça; Supremo Tribunal Federal; Tribunal de Contas da União",
      "relator": "Benjamin Zymler",
      "colegiado": "Plenário",
      "natureza": null,
      "data": "2026-05-19T00:00:00+00:00",
      "data_sessao": "2026-05-19T00:00:00+00:00",
      "data_julgamento": null,
      "edicao_btcu": 23281,
      "link_tcu": null
    },
    {
      "fonte": "Pauta",
      "secao": "pauta",
      "status": "Em pauta",
      "status_descricao": "Aguardando julgamento em sessão marcada",
      "acordao": null,
      "orgaos": [
        "MPO"
      ],
      "temas": [
        "Orçamento e execução"
      ],
      "confianca": "unidade_jurisdicionada",
      "vinculo": "compartilhado",
      "classe": "materia",
      "relevancia": 1.8,
      "processo": "025.632/2024-8",
      "processo_id": "02563220248",
      "assunto": "Auditoria operacional com aspectos de conformidade sobre a execução de  programas/projetos públicos custeados com recursos públicos que não transitam  diretamente pelo do Orçamento Geral da União",
      "unidade_jurisdicionada": "Banco Central do Brasil; Banco do Brasil S.a.; Banco Nacional de Desenvolvimento Econômico e Social; Caixa Econômica Federal; Empresa Gestora de Ativos; Ministério da Fazenda; Ministério do Planejamento e Orçamento",
      "relator": "Bruno Dantas",
      "colegiado": "Plenário",
      "natureza": null,
      "data": "2026-05-19T00:00:00+00:00",
      "data_sessao": "2026-05-19T00:00:00+00:00",
      "data_julgamento": null,
      "edicao_btcu": 23281,
      "link_tcu": null
    }
  ],
  "ultima_atualizacao": "24/07/2026 às 14:25",
  "ultima_atualizacao_iso": "2026-07-24T14:25:22.291776+00:00",
  "pautas_futuras": [
    {
      "processo": "025.632/2024-8",
      "processo_id": "02563220248",
      "data_sessao": "2025-06-18T00:00:00+00:00",
      "colegiado": "Plenário",
      "relator": "BRUNO DANTAS",
      "natureza": "CONTROLE EXTERNO",
      "tipo": "RELATÓRIO DE AUDITORIA"
    },
    {
      "processo": "024.241/2025-3",
      "processo_id": "02424120253",
      "data_sessao": "2026-05-19T00:00:00+00:00",
      "colegiado": "Plenário",
      "relator": "BENJAMIN ZYMLER",
      "natureza": "CONTROLE EXTERNO",
      "tipo": "RELATÓRIO DE ACOMPANHAMENTO"
    },
    {
      "processo": "022.756/2025-6",
      "processo_id": "02275620256",
      "data_sessao": "2026-05-27T00:00:00+00:00",
      "colegiado": "Plenário",
      "relator": "BENJAMIN ZYMLER",
      "natureza": "CONTROLE EXTERNO",
      "tipo": "RELATÓRIO DE AUDITORIA"
    },
    {
      "processo": "025.632/2024-8",
      "processo_id": "02563220248",
      "data_sessao": "2026-05-27T00:00:00+00:00",
      "colegiado": "Plenário",
      "relator": "BRUNO DANTAS",
      "natureza": "CONTROLE EXTERNO",
      "tipo": "RELATÓRIO DE AUDITORIA"
    },
    {
      "processo": "025.632/2024-8",
      "processo_id": "02563220248",
      "data_sessao": "2026-07-15T00:00:00+00:00",
      "colegiado": "Plenário",
      "relator": "BRUNO DANTAS",
      "natureza": "CONTROLE EXTERNO",
      "tipo": "RELATÓRIO DE AUDITORIA"
    }
  ],
  "fontes_indisponiveis": [
    "Acórdãos"
  ],
  "total_itens": 3
}